LICENSE
README.md
setup.py
calbert/CalBERT.py
calbert/CalBERTDataset.py
calbert/SiamesePreTrainer.py
calbert/__init__.py
calbert.egg-info/PKG-INFO
calbert.egg-info/SOURCES.txt
calbert.egg-info/dependency_links.txt
calbert.egg-info/requires.txt
calbert.egg-info/top_level.txt