Metadata-Version: 2.1
Name: calbert
Version: 1.0.2
Summary: Code-mixed Adaptive Language representations using BERT
Home-page: https://github.com/aditeyabaral/calbert
Download-URL: https://pypi.org/project/calbert/
Author: Aditeya Baral
Author-email: aditeya.baral@gmail.com
Maintainer: Aronya Baksy
Maintainer-email: abaksy@gmail.com
License: MIT
Keywords: NLP deep learning transformer pytorch BERT
Platform: UNKNOWN
Classifier: Development Status :: 5 - Production/Stable
Classifier: Intended Audience :: Developers
Classifier: Intended Audience :: Education
Classifier: Intended Audience :: Science/Research
Classifier: License :: OSI Approved :: MIT License
Classifier: Operating System :: OS Independent
Classifier: Programming Language :: Python :: 3.7
Classifier: Programming Language :: Python :: 3.8
Classifier: Programming Language :: Python :: 3.9
Classifier: Programming Language :: Python :: 3.10
Classifier: Topic :: Scientific/Engineering :: Artificial Intelligence
Requires-Python: >=3.7.0
License-File: LICENSE
